pytest_html5/__init__.py
pytest_html5/extras.py
pytest_html5/hooks.py
pytest_html5/plugin.py
pytest_html5/sttc/echarts.min.js
pytest_html5/sttc/main.js
pytest_html5/sttc/style.css
pytest_html5-1.6.dist-info/licenses/LICENSE
pytest_html5-1.6.dist-info/METADATA
pytest_html5-1.6.dist-info/WHEEL
pytest_html5-1.6.dist-info/entry_points.txt
pytest_html5-1.6.dist-info/top_level.txt
pytest_html5-1.6.dist-info/RECORD
