Metadata-Version: 2.4
Name: pytest-html5
Version: 1.6
Summary: the best report for pytest
Author: teark
Author-email: 913355434@qq.com
Classifier: Programming Language :: Python :: 3
Classifier: License :: OSI Approved :: MIT License
Classifier: Operating System :: OS Independent
Requires-Python: >=3.6
License-File: LICENSE
Requires-Dist: pyecharts
Requires-Dist: pillow
Requires-Dist: py
Requires-Dist: lxml
Dynamic: author
Dynamic: author-email
Dynamic: classifier
Dynamic: description
Dynamic: description-content-type
Dynamic: license-file
Dynamic: requires-dist
Dynamic: requires-python
Dynamic: summary
